README.rst
setup.py
kivu/__init__.py
kivu.egg-info/PKG-INFO
kivu.egg-info/SOURCES.txt
kivu.egg-info/dependency_links.txt
kivu.egg-info/not-zip-safe
kivu.egg-info/top_level.txt