Metadata-Version: 1.0
Name: kivu
Version: 0.1
Summary: Asset management utilities for python
Home-page: https://github.com/altfund/kivu
Author: Altfund Capital
Author-email: altfund@altfund.org
License: GNU
Platform: UNKNOWN
